kepler/__init__.py
kepler/event.py
kepler/measurement.py
kepler/memory.py
kepler/report.py
kepler/scope.py
kepler/timer.py
kepler/reporting/__init__.py
kepler/reporting/brail.py
kepler/reporting/color.py
kepler/reporting/format.py
kepler/reporting/reporter.py
kepler/reporting/statistic.py
kepler/reporting/units.py
kepler-0.3.0.dist-info/METADATA
kepler-0.3.0.dist-info/WHEEL
kepler-0.3.0.dist-info/RECORD
