Metadata-Version: 2.4
Name: kepler
Version: 0.3.0
Summary: Fast, easy, pretty and readable program instrumentation.
Project-URL: Homepage, https://github.com/bethebunny/kepler
Project-URL: Documentation, https://github.com/bethebunny/kepler
Project-URL: Repository, https://github.com/bethebunny/kepler
Project-URL: Issues, https://github.com/bethebunny/kepler/issues
Project-URL: Changelog, https://github.com/bethebunny/kepler/releases
Author-email: Stef Lindall <bethebunny@gmail.com>
License: Copyright 2024 Stef Lindall, License BSD-3-Clause
Keywords: async,asyncio,instrument,instrumentation,profile,rich
Classifier: Development Status :: 4 - Beta
Classifier: Intended Audience :: Developers
Classifier: License :: OSI Approved :: BSD License
Classifier: Programming Language :: Python :: 3
Classifier: Programming Language :: Python :: 3.9
Classifier: Programming Language :: Python :: 3.10
Classifier: Programming Language :: Python :: 3.11
Classifier: Programming Language :: Python :: 3.12
Classifier: Programming Language :: Python :: 3.13
Classifier: Topic :: Software Development :: Libraries :: Python Modules
Classifier: Topic :: System :: Monitoring
Requires-Python: >=3.10
Requires-Dist: numpy
Requires-Dist: psutil
Requires-Dist: rich
